[
  {
    "coord": {
      "lon": -135.3153,
      "lat": 59.4554
    },
    "weather": [
      {
        "id": 804,
        "main": "Clouds",
        "description": "overcast clouds",
        "icon": "04n"
      }
    ],
    "base": "stations",
    "main": {
      "temp": 16.5,
      "feels_like": 16.06,
      "temp_min": 16.5,
      "temp_max": 16.5,
      "pressure": 1021,
      "humidity": 71,
      "sea_level": 1021,
      "grnd_level": 1020
    },
    "visibility": 10000,
    "wind": {
      "speed": 0.96,
      "deg": 27,
      "gust": 1.03
    },
    "clouds": {
      "all": 99
    },
    "dt": 1781942377,
    "sys": {
      "country": "US",
      "sunrise": 1781869373,
      "sunset": 1781936545
    },
    "timezone": -28800,
    "id": 5846893,
    "name": "Haines",
    "cod": 200
  },
  {
    "coord": {
      "lon": -135.3153,
      "lat": 59.4554
    },
    "weather": [
      {
        "id": 800,
        "main": "Clear",
        "description": "clear sky",
        "icon": "01n"
      }
    ],
    "base": "stations",
    "main": {
      "temp": 14.09,
      "feels_like": 14.06,
      "temp_min": 14.09,
      "temp_max": 14.09,
      "pressure": 1021,
      "humidity": 96,
      "sea_level": 1021,
      "grnd_level": 1020
    },
    "visibility": 2336,
    "wind": {
      "speed": 0.38,
      "deg": 119,
      "gust": 1.08
    },
    "clouds": {
      "all": 7
    },
    "dt": 1782029823,
    "sys": {
      "country": "US",
      "sunrise": 1782042188,
      "sunset": 1782109379
    },
    "timezone": -28800,
    "id": 5846893,
    "name": "Haines",
    "cod": 200
  },
  {
    "coord": {
      "lon": -135.3153,
      "lat": 59.4554
    },
    "weather": [
      {
        "id": 803,
        "main": "Clouds",
        "description": "broken clouds",
        "icon": "04n"
      }
    ],
    "base": "stations",
    "main": {
      "temp": 14.04,
      "feels_like": 14.01,
      "temp_min": 14.04,
      "temp_max": 14.04,
      "pressure": 1021,
      "humidity": 96,
      "sea_level": 1021,
      "grnd_level": 1020
    },
    "visibility": 2869,
    "wind": {
      "speed": 0.92,
      "deg": 134,
      "gust": 1.35
    },
    "clouds": {
      "all": 64
    },
    "dt": 1782117828,
    "sys": {
      "country": "US",
      "sunrise": 1782128604,
      "sunset": 1782195787
    },
    "timezone": -28800,
    "id": 5846893,
    "name": "Haines",
    "cod": 200
  },
  {
    "coord": {
      "lon": -135.3153,
      "lat": 59.4554
    },
    "weather": [
      {
        "id": 500,
        "main": "Rain",
        "description": "light rain",
        "icon": "10n"
      }
    ],
    "base": "stations",
    "main": {
      "temp": 13.95,
      "feels_like": 13.99,
      "temp_min": 13.95,
      "temp_max": 13.95,
      "pressure": 1022,
      "humidity": 99,
      "sea_level": 1022,
      "grnd_level": 1021
    },
    "visibility": 85,
    "wind": {
      "speed": 2.9,
      "deg": 190,
      "gust": 6.31
    },
    "rain": {
      "1h": 0.53
    },
    "clouds": {
      "all": 100
    },
    "dt": 1782201591,
    "sys": {
      "country": "US",
      "sunrise": 1782128604,
      "sunset": 1782195787
    },
    "timezone": -28800,
    "id": 5846893,
    "name": "Haines",
    "cod": 200
  },
  {
    "coord": {
      "lon": -135.3153,
      "lat": 59.4554
    },
    "weather": [
      {
        "id": 803,
        "main": "Clouds",
        "description": "broken clouds",
        "icon": "04n"
      }
    ],
    "base": "stations",
    "main": {
      "temp": 12.71,
      "feels_like": 12.44,
      "temp_min": 12.71,
      "temp_max": 12.71,
      "pressure": 1021,
      "humidity": 92,
      "sea_level": 1021,
      "grnd_level": 1020
    },
    "visibility": 10000,
    "wind": {
      "speed": 0.48,
      "deg": 161,
      "gust": 0.9
    },
    "clouds": {
      "all": 60
    },
    "dt": 1782287835,
    "sys": {
      "country": "US",
      "sunrise": 1782215024,
      "sunset": 1782282191
    },
    "timezone": -28800,
    "id": 5846893,
    "name": "Haines",
    "cod": 200
  },
  {
    "coord": {
      "lon": -135.3153,
      "lat": 59.4554
    },
    "weather": [
      {
        "id": 804,
        "main": "Clouds",
        "description": "overcast clouds",
        "icon": "04n"
      }
    ],
    "base": "stations",
    "main": {
      "temp": 12.22,
      "feels_like": 11.95,
      "temp_min": 12.22,
      "temp_max": 12.22,
      "pressure": 1009,
      "humidity": 94,
      "sea_level": 1009,
      "grnd_level": 1008
    },
    "visibility": 10000,
    "wind": {
      "speed": 1.81,
      "deg": 5,
      "gust": 2.05
    },
    "clouds": {
      "all": 91
    },
    "dt": 1782374272,
    "sys": {
      "country": "US",
      "sunrise": 1782301450,
      "sunset": 1782368589
    },
    "timezone": -28800,
    "id": 5846893,
    "name": "Haines",
    "cod": 200
  },
  {
    "coord": {
      "lon": -135.3153,
      "lat": 59.4554
    },
    "weather": [
      {
        "id": 804,
        "main": "Clouds",
        "description": "overcast clouds",
        "icon": "04n"
      }
    ],
    "base": "stations",
    "main": {
      "temp": 11.48,
      "feels_like": 11.24,
      "temp_min": 11.48,
      "temp_max": 11.48,
      "pressure": 1008,
      "humidity": 98,
      "sea_level": 1008,
      "grnd_level": 1007
    },
    "visibility": 2536,
    "wind": {
      "speed": 0.49,
      "deg": 218,
      "gust": 0.91
    },
    "clouds": {
      "all": 100
    },
    "dt": 1782460950,
    "sys": {
      "country": "US",
      "sunrise": 1782474317,
      "sunset": 1782541370
    },
    "timezone": -28800,
    "id": 5846893,
    "name": "Haines",
    "cod": 200
  },
  {
    "coord": {
      "lon": -135.3153,
      "lat": 59.4554
    },
    "weather": [
      {
        "id": 803,
        "main": "Clouds",
        "description": "broken clouds",
        "icon": "04n"
      }
    ],
    "base": "stations",
    "main": {
      "temp": 13.03,
      "feels_like": 12.84,
      "temp_min": 13.03,
      "temp_max": 13.03,
      "pressure": 1009,
      "humidity": 94,
      "sea_level": 1009,
      "grnd_level": 1008
    },
    "visibility": 4313,
    "wind": {
      "speed": 0.53,
      "deg": 50,
      "gust": 1.1
    },
    "clouds": {
      "all": 75
    },
    "dt": 1782546157,
    "sys": {
      "country": "US",
      "sunrise": 1782474317,
      "sunset": 1782541370
    },
    "timezone": -28800,
    "id": 5846893,
    "name": "Haines",
    "cod": 200
  },
  {
    "coord": {
      "lon": -135.3153,
      "lat": 59.4554
    },
    "weather": [
      {
        "id": 500,
        "main": "Rain",
        "description": "light rain",
        "icon": "10n"
      }
    ],
    "base": "stations",
    "main": {
      "temp": 11.52,
      "feels_like": 11.31,
      "temp_min": 11.52,
      "temp_max": 11.52,
      "pressure": 1018,
      "humidity": 99,
      "sea_level": 1018,
      "grnd_level": 1017
    },
    "visibility": 69,
    "wind": {
      "speed": 3.17,
      "deg": 193,
      "gust": 5.23
    },
    "rain": {
      "1h": 0.18
    },
    "clouds": {
      "all": 100
    },
    "dt": 1782633589,
    "sys": {
      "country": "US",
      "sunrise": 1782560757,
      "sunset": 1782627753
    },
    "timezone": -28800,
    "id": 5846893,
    "name": "Haines",
    "cod": 200
  },
  {
    "coord": {
      "lon": -135.3153,
      "lat": 59.4554
    },
    "weather": [
      {
        "id": 804,
        "main": "Clouds",
        "description": "overcast clouds",
        "icon": "04n"
      }
    ],
    "base": "stations",
    "main": {
      "temp": 11.16,
      "feels_like": 10.92,
      "temp_min": 11.16,
      "temp_max": 11.16,
      "pressure": 1022,
      "humidity": 99,
      "sea_level": 1022,
      "grnd_level": 1021
    },
    "visibility": 110,
    "wind": {
      "speed": 2.44,
      "deg": 196,
      "gust": 4.14
    },
    "clouds": {
      "all": 100
    },
    "dt": 1782721713,
    "sys": {
      "country": "US",
      "sunrise": 1782733653,
      "sunset": 1782800503
    },
    "timezone": -28800,
    "id": 5846893,
    "name": "Haines",
    "cod": 200
  }
]