[
  {
    "coord": {
      "lon": -135.3153,
      "lat": 59.4554
    },
    "weather": [
      {
        "id": 803,
        "main": "Clouds",
        "description": "broken clouds",
        "icon": "04n"
      }
    ],
    "base": "stations",
    "main": {
      "temp": 8.97,
      "feels_like": 8.97,
      "temp_min": 8.97,
      "temp_max": 11.01,
      "pressure": 998,
      "humidity": 100,
      "sea_level": 998,
      "grnd_level": 997
    },
    "visibility": 10000,
    "wind": {
      "speed": 0,
      "deg": 0
    },
    "clouds": {
      "all": 75
    },
    "dt": 1727247008,
    "sys": {
      "type": 1,
      "id": 7704,
      "country": "US",
      "sunrise": 1727189506,
      "sunset": 1727232859
    },
    "timezone": -28800,
    "id": 5846893,
    "name": "Haines",
    "cod": 200
  },
  {
    "coord": {
      "lon": -135.3153,
      "lat": 59.4554
    },
    "weather": [
      {
        "id": 500,
        "main": "Rain",
        "description": "light rain",
        "icon": "10n"
      }
    ],
    "base": "stations",
    "main": {
      "temp": 8.97,
      "feels_like": 6.68,
      "temp_min": 8.97,
      "temp_max": 10.01,
      "pressure": 1002,
      "humidity": 87,
      "sea_level": 1002,
      "grnd_level": 1001
    },
    "visibility": 10000,
    "wind": {
      "speed": 4.12,
      "deg": 200
    },
    "rain": {
      "1h": 0.25
    },
    "clouds": {
      "all": 100
    },
    "dt": 1727333412,
    "sys": {
      "type": 1,
      "id": 7704,
      "country": "US",
      "sunrise": 1727276043,
      "sunset": 1727319079
    },
    "timezone": -28800,
    "id": 5846893,
    "name": "Haines",
    "cod": 200
  },
  {
    "coord": {
      "lon": -135.3153,
      "lat": 59.4554
    },
    "weather": [
      {
        "id": 800,
        "main": "Clear",
        "description": "clear sky",
        "icon": "01n"
      }
    ],
    "base": "stations",
    "main": {
      "temp": 4.97,
      "feels_like": 4.97,
      "temp_min": 4.97,
      "temp_max": 8.01,
      "pressure": 1000,
      "humidity": 100,
      "sea_level": 1000,
      "grnd_level": 999
    },
    "visibility": 10000,
    "wind": {
      "speed": 0,
      "deg": 0
    },
    "clouds": {
      "all": 0
    },
    "dt": 1727419819,
    "sys": {
      "type": 1,
      "id": 7704,
      "country": "US",
      "sunrise": 1727362580,
      "sunset": 1727405299
    },
    "timezone": -28800,
    "id": 5846893,
    "name": "Haines",
    "cod": 200
  },
  {
    "coord": {
      "lon": -135.3153,
      "lat": 59.4554
    },
    "weather": [
      {
        "id": 500,
        "main": "Rain",
        "description": "light rain",
        "icon": "10n"
      }
    ],
    "base": "stations",
    "main": {
      "temp": 9.97,
      "feels_like": 6.84,
      "temp_min": 9.97,
      "temp_max": 10.01,
      "pressure": 1015,
      "humidity": 76,
      "sea_level": 1015,
      "grnd_level": 1014
    },
    "visibility": 10000,
    "wind": {
      "speed": 7.2,
      "deg": 210,
      "gust": 10.8
    },
    "rain": {
      "1h": 0.11
    },
    "clouds": {
      "all": 100
    },
    "dt": 1727506140,
    "sys": {
      "type": 1,
      "id": 7704,
      "country": "US",
      "sunrise": 1727449118,
      "sunset": 1727491520
    },
    "timezone": -28800,
    "id": 5846893,
    "name": "Haines",
    "cod": 200
  },
  {
    "coord": {
      "lon": -135.3153,
      "lat": 59.4554
    },
    "weather": [
      {
        "id": 803,
        "main": "Clouds",
        "description": "broken clouds",
        "icon": "04n"
      }
    ],
    "base": "stations",
    "main": {
      "temp": 5.97,
      "feels_like": 5.97,
      "temp_min": 5.97,
      "temp_max": 8.01,
      "pressure": 1016,
      "humidity": 93,
      "sea_level": 1016,
      "grnd_level": 1015
    },
    "visibility": 10000,
    "wind": {
      "speed": 0,
      "deg": 0
    },
    "clouds": {
      "all": 75
    },
    "dt": 1727592560,
    "sys": {
      "type": 1,
      "id": 7704,
      "country": "US",
      "sunrise": 1727535655,
      "sunset": 1727577740
    },
    "timezone": -28800,
    "id": 5846893,
    "name": "Haines",
    "cod": 200
  },
  {
    "coord": {
      "lon": -135.3153,
      "lat": 59.4554
    },
    "weather": [
      {
        "id": 804,
        "main": "Clouds",
        "description": "overcast clouds",
        "icon": "04n"
      }
    ],
    "base": "stations",
    "main": {
      "temp": 6.97,
      "feels_like": 6.97,
      "temp_min": 6.01,
      "temp_max": 6.97,
      "pressure": 1024,
      "humidity": 93,
      "sea_level": 1024,
      "grnd_level": 1023
    },
    "visibility": 10000,
    "wind": {
      "speed": 0,
      "deg": 0
    },
    "clouds": {
      "all": 100
    },
    "dt": 1727679028,
    "sys": {
      "type": 1,
      "id": 7704,
      "country": "US",
      "sunrise": 1727622193,
      "sunset": 1727663961
    },
    "timezone": -28800,
    "id": 5846893,
    "name": "Haines",
    "cod": 200
  },
  {
    "coord": {
      "lon": -135.3153,
      "lat": 59.4554
    },
    "weather": [
      {
        "id": 500,
        "main": "Rain",
        "description": "light rain",
        "icon": "10n"
      }
    ],
    "base": "stations",
    "main": {
      "temp": 9.97,
      "feels_like": 7.7,
      "temp_min": 7.01,
      "temp_max": 9.97,
      "pressure": 1005,
      "humidity": 57,
      "sea_level": 1005,
      "grnd_level": 1004
    },
    "visibility": 10000,
    "wind": {
      "speed": 4.63,
      "deg": 20,
      "gust": 11.32
    },
    "rain": {
      "1h": 0.55
    },
    "clouds": {
      "all": 100
    },
    "dt": 1727765438,
    "sys": {
      "type": 1,
      "id": 7704,
      "country": "US",
      "sunrise": 1727708731,
      "sunset": 1727750183
    },
    "timezone": -28800,
    "id": 5846893,
    "name": "Haines",
    "cod": 200
  },
  {
    "coord": {
      "lon": -135.3153,
      "lat": 59.4554
    },
    "weather": [
      {
        "id": 800,
        "main": "Clear",
        "description": "clear sky",
        "icon": "01n"
      }
    ],
    "base": "stations",
    "main": {
      "temp": 7.97,
      "feels_like": 7.29,
      "temp_min": 7.97,
      "temp_max": 8.01,
      "pressure": 1010,
      "humidity": 71,
      "sea_level": 1010,
      "grnd_level": 1009
    },
    "visibility": 10000,
    "wind": {
      "speed": 1.54,
      "deg": 280
    },
    "clouds": {
      "all": 0
    },
    "dt": 1727851829,
    "sys": {
      "type": 1,
      "id": 7704,
      "country": "US",
      "sunrise": 1727795270,
      "sunset": 1727836404
    },
    "timezone": -28800,
    "id": 5846893,
    "name": "Haines",
    "cod": 200
  },
  {
    "coord": {
      "lon": -135.3153,
      "lat": 59.4554
    },
    "weather": [
      {
        "id": 500,
        "main": "Rain",
        "description": "light rain",
        "icon": "10n"
      }
    ],
    "base": "stations",
    "main": {
      "temp": 9.97,
      "feels_like": 7.5,
      "temp_min": 9.97,
      "temp_max": 10.01,
      "pressure": 1018,
      "humidity": 76,
      "sea_level": 1018,
      "grnd_level": 1017
    },
    "visibility": 10000,
    "wind": {
      "speed": 5.14,
      "deg": 200,
      "gust": 11.32
    },
    "rain": {
      "1h": 0.31
    },
    "clouds": {
      "all": 100
    },
    "dt": 1727938203,
    "sys": {
      "type": 1,
      "id": 7704,
      "country": "US",
      "sunrise": 1727881808,
      "sunset": 1727922626
    },
    "timezone": -28800,
    "id": 5846893,
    "name": "Haines",
    "cod": 200
  },
  {
    "coord": {
      "lon": -135.3153,
      "lat": 59.4554
    },
    "weather": [
      {
        "id": 804,
        "main": "Clouds",
        "description": "overcast clouds",
        "icon": "04n"
      }
    ],
    "base": "stations",
    "main": {
      "temp": 6.97,
      "feels_like": 6.97,
      "temp_min": 6.97,
      "temp_max": 8.01,
      "pressure": 1009,
      "humidity": 93,
      "sea_level": 1009,
      "grnd_level": 1008
    },
    "visibility": 10000,
    "wind": {
      "speed": 0,
      "deg": 0
    },
    "clouds": {
      "all": 100
    },
    "dt": 1728024627,
    "sys": {
      "type": 1,
      "id": 7704,
      "country": "US",
      "sunrise": 1727968347,
      "sunset": 1728008848
    },
    "timezone": -28800,
    "id": 5846893,
    "name": "Haines",
    "cod": 200
  }
]