[
  {
    "coord": {
      "lon": -135.3153,
      "lat": 59.4554
    },
    "weather": [
      {
        "id": 804,
        "main": "Clouds",
        "description": "overcast clouds",
        "icon": "04n"
      }
    ],
    "base": "stations",
    "main": {
      "temp": 2.97,
      "feels_like": -4.03,
      "temp_min": 1.01,
      "temp_max": 2.97,
      "pressure": 996,
      "humidity": 52,
      "sea_level": 996,
      "grnd_level": 995
    },
    "visibility": 10000,
    "wind": {
      "speed": 13.89,
      "deg": 40,
      "gust": 20.58
    },
    "clouds": {
      "all": 100
    },
    "dt": 1734850139,
    "sys": {
      "type": 1,
      "id": 7704,
      "country": "US",
      "sunrise": 1734803913,
      "sunset": 1734825646
    },
    "timezone": -32400,
    "id": 5846893,
    "name": "Haines",
    "cod": 200
  },
  {
    "coord": {
      "lon": -135.3153,
      "lat": 59.4554
    },
    "weather": [
      {
        "id": 500,
        "main": "Rain",
        "description": "light rain",
        "icon": "10n"
      }
    ],
    "base": "stations",
    "main": {
      "temp": 1.97,
      "feels_like": 1.97,
      "temp_min": 1.97,
      "temp_max": 2.01,
      "pressure": 988,
      "humidity": 100,
      "sea_level": 988,
      "grnd_level": 987
    },
    "visibility": 10000,
    "wind": {
      "speed": 0,
      "deg": 0
    },
    "rain": {
      "1h": 0.27
    },
    "clouds": {
      "all": 100
    },
    "dt": 1734936597,
    "sys": {
      "type": 1,
      "id": 7704,
      "country": "US",
      "sunrise": 1734890338,
      "sunset": 1734912079
    },
    "timezone": -32400,
    "id": 5846893,
    "name": "Haines",
    "cod": 200
  },
  {
    "coord": {
      "lon": -135.3153,
      "lat": 59.4554
    },
    "weather": [
      {
        "id": 500,
        "main": "Rain",
        "description": "light rain",
        "icon": "10n"
      }
    ],
    "base": "stations",
    "main": {
      "temp": 1.97,
      "feels_like": 0.43,
      "temp_min": 1.97,
      "temp_max": 4.01,
      "pressure": 996,
      "humidity": 93,
      "sea_level": 996,
      "grnd_level": 995
    },
    "visibility": 10000,
    "wind": {
      "speed": 1.54,
      "deg": 20
    },
    "rain": {
      "1h": 0.11
    },
    "clouds": {
      "all": 100
    },
    "dt": 1735022976,
    "sys": {
      "type": 1,
      "id": 7704,
      "country": "US",
      "sunrise": 1734976759,
      "sunset": 1734998516
    },
    "timezone": -32400,
    "id": 5846893,
    "name": "Haines",
    "cod": 200
  },
  {
    "coord": {
      "lon": -135.3153,
      "lat": 59.4554
    },
    "weather": [
      {
        "id": 500,
        "main": "Rain",
        "description": "light rain",
        "icon": "10n"
      }
    ],
    "base": "stations",
    "main": {
      "temp": 4.97,
      "feels_like": -0.25,
      "temp_min": 4.97,
      "temp_max": 5.01,
      "pressure": 991,
      "humidity": 81,
      "sea_level": 991,
      "grnd_level": 990
    },
    "visibility": 10000,
    "wind": {
      "speed": 9.26,
      "deg": 210,
      "gust": 13.89
    },
    "rain": {
      "1h": 0.52
    },
    "clouds": {
      "all": 100
    },
    "dt": 1735109376,
    "sys": {
      "type": 1,
      "id": 7704,
      "country": "US",
      "sunrise": 1735063173,
      "sunset": 1735084959
    },
    "timezone": -32400,
    "id": 5846893,
    "name": "Haines",
    "cod": 200
  },
  {
    "coord": {
      "lon": -135.3153,
      "lat": 59.4554
    },
    "weather": [
      {
        "id": 500,
        "main": "Rain",
        "description": "light rain",
        "icon": "10n"
      }
    ],
    "base": "stations",
    "main": {
      "temp": 5.97,
      "feels_like": 3.61,
      "temp_min": 2.01,
      "temp_max": 5.97,
      "pressure": 978,
      "humidity": 61,
      "sea_level": 978,
      "grnd_level": 977
    },
    "visibility": 10000,
    "wind": {
      "speed": 3.09,
      "deg": 0
    },
    "rain": {
      "1h": 0.13
    },
    "clouds": {
      "all": 100
    },
    "dt": 1735195783,
    "sys": {
      "type": 1,
      "id": 7704,
      "country": "US",
      "sunrise": 1735149583,
      "sunset": 1735171407
    },
    "timezone": -32400,
    "id": 5846893,
    "name": "Haines",
    "cod": 200
  },
  {
    "coord": {
      "lon": -135.3153,
      "lat": 59.4554
    },
    "weather": [
      {
        "id": 802,
        "main": "Clouds",
        "description": "scattered clouds",
        "icon": "03n"
      }
    ],
    "base": "stations",
    "main": {
      "temp": 5.97,
      "feels_like": 1.69,
      "temp_min": 5.97,
      "temp_max": 6.01,
      "pressure": 992,
      "humidity": 75,
      "sea_level": 992,
      "grnd_level": 991
    },
    "visibility": 10000,
    "wind": {
      "speed": 7.2,
      "deg": 200,
      "gust": 12.86
    },
    "clouds": {
      "all": 40
    },
    "dt": 1735282174,
    "sys": {
      "type": 1,
      "id": 7704,
      "country": "US",
      "sunrise": 1735235987,
      "sunset": 1735257860
    },
    "timezone": -32400,
    "id": 5846893,
    "name": "Haines",
    "cod": 200
  },
  {
    "coord": {
      "lon": -135.3153,
      "lat": 59.4554
    },
    "weather": [
      {
        "id": 804,
        "main": "Clouds",
        "description": "overcast clouds",
        "icon": "04n"
      }
    ],
    "base": "stations",
    "main": {
      "temp": 0.97,
      "feels_like": -0.71,
      "temp_min": 0.97,
      "temp_max": 4.01,
      "pressure": 999,
      "humidity": 93,
      "sea_level": 999,
      "grnd_level": 998
    },
    "visibility": 10000,
    "wind": {
      "speed": 1.54,
      "deg": 30
    },
    "clouds": {
      "all": 100
    },
    "dt": 1735368537,
    "sys": {
      "type": 1,
      "id": 7704,
      "country": "US",
      "sunrise": 1735322386,
      "sunset": 1735344319
    },
    "timezone": -32400,
    "id": 5846893,
    "name": "Haines",
    "cod": 200
  },
  {
    "coord": {
      "lon": -135.3153,
      "lat": 59.4554
    },
    "weather": [
      {
        "id": 804,
        "main": "Clouds",
        "description": "overcast clouds",
        "icon": "04n"
      }
    ],
    "base": "stations",
    "main": {
      "temp": 0.97,
      "feels_like": 0.97,
      "temp_min": 0.97,
      "temp_max": 2.01,
      "pressure": 1008,
      "humidity": 100,
      "sea_level": 1008,
      "grnd_level": 1007
    },
    "visibility": 10000,
    "wind": {
      "speed": 0,
      "deg": 0
    },
    "clouds": {
      "all": 100
    },
    "dt": 1735454942,
    "sys": {
      "type": 1,
      "id": 7704,
      "country": "US",
      "sunrise": 1735408780,
      "sunset": 1735430782
    },
    "timezone": -32400,
    "id": 5846893,
    "name": "Haines",
    "cod": 200
  },
  {
    "coord": {
      "lon": -135.3153,
      "lat": 59.4554
    },
    "weather": [
      {
        "id": 800,
        "main": "Clear",
        "description": "clear sky",
        "icon": "01n"
      }
    ],
    "base": "stations",
    "main": {
      "temp": 1.97,
      "feels_like": -0.23,
      "temp_min": 0.01,
      "temp_max": 1.97,
      "pressure": 1024,
      "humidity": 51,
      "sea_level": 1024,
      "grnd_level": 1023
    },
    "visibility": 10000,
    "wind": {
      "speed": 2.06,
      "deg": 320
    },
    "clouds": {
      "all": 0
    },
    "dt": 1735541402,
    "sys": {
      "type": 1,
      "id": 7704,
      "country": "US",
      "sunrise": 1735495168,
      "sunset": 1735517250
    },
    "timezone": -32400,
    "id": 5846893,
    "name": "Haines",
    "cod": 200
  },
  {
    "coord": {
      "lon": -135.3153,
      "lat": 59.4554
    },
    "weather": [
      {
        "id": 800,
        "main": "Clear",
        "description": "clear sky",
        "icon": "01n"
      }
    ],
    "base": "stations",
    "main": {
      "temp": 0.97,
      "feels_like": -5.68,
      "temp_min": -2.99,
      "temp_max": 0.97,
      "pressure": 1034,
      "humidity": 51,
      "sea_level": 1034,
      "grnd_level": 1033
    },
    "visibility": 10000,
    "wind": {
      "speed": 9.77,
      "deg": 30,
      "gust": 14.4
    },
    "clouds": {
      "all": 0
    },
    "dt": 1735627770,
    "sys": {
      "type": 1,
      "id": 7704,
      "country": "US",
      "sunrise": 1735581552,
      "sunset": 1735603723
    },
    "timezone": -32400,
    "id": 5846893,
    "name": "Haines",
    "cod": 200
  }
]