[
  {
    "coord": {
      "lon": -125.2317,
      "lat": 58.8478
    },
    "weather": [
      {
        "id": 804,
        "main": "Clouds",
        "description": "overcast clouds",
        "icon": "04n"
      }
    ],
    "base": "stations",
    "main": {
      "temp": -8.39,
      "feels_like": -12.32,
      "temp_min": -8.39,
      "temp_max": -8.39,
      "pressure": 1011,
      "humidity": 95,
      "sea_level": 1011,
      "grnd_level": 924
    },
    "visibility": 10000,
    "wind": {
      "speed": 2.06,
      "deg": 235,
      "gust": 1.65
    },
    "clouds": {
      "all": 99
    },
    "dt": 1731653479,
    "sys": {
      "country": "CA",
      "sunrise": 1731600680,
      "sunset": 1731628789
    },
    "timezone": -25200,
    "id": 6064168,
    "name": "Magnum Mine",
    "cod": 200
  },
  {
    "coord": {
      "lon": -125.2317,
      "lat": 58.8478
    },
    "weather": [
      {
        "id": 800,
        "main": "Clear",
        "description": "clear sky",
        "icon": "01n"
      }
    ],
    "base": "stations",
    "main": {
      "temp": -5.51,
      "feels_like": -10.72,
      "temp_min": -5.51,
      "temp_max": -5.51,
      "pressure": 998,
      "humidity": 86,
      "sea_level": 998,
      "grnd_level": 913
    },
    "visibility": 10000,
    "wind": {
      "speed": 3.62,
      "deg": 222,
      "gust": 4.48
    },
    "clouds": {
      "all": 8
    },
    "dt": 1731739778,
    "sys": {
      "country": "CA",
      "sunrise": 1731687222,
      "sunset": 1731715070
    },
    "timezone": -25200,
    "id": 6064168,
    "name": "Magnum Mine",
    "cod": 200
  },
  {
    "coord": {
      "lon": -125.2317,
      "lat": 58.8478
    },
    "weather": [
      {
        "id": 804,
        "main": "Clouds",
        "description": "overcast clouds",
        "icon": "04n"
      }
    ],
    "base": "stations",
    "main": {
      "temp": -9.73,
      "feels_like": -12.56,
      "temp_min": -9.73,
      "temp_max": -9.73,
      "pressure": 992,
      "humidity": 95,
      "sea_level": 992,
      "grnd_level": 905
    },
    "visibility": 10000,
    "wind": {
      "speed": 1.37,
      "deg": 215,
      "gust": 1.2
    },
    "clouds": {
      "all": 95
    },
    "dt": 1731826199,
    "sys": {
      "country": "CA",
      "sunrise": 1731773763,
      "sunset": 1731801352
    },
    "timezone": -25200,
    "id": 6064168,
    "name": "Magnum Mine",
    "cod": 200
  },
  {
    "coord": {
      "lon": -125.2317,
      "lat": 58.8478
    },
    "weather": [
      {
        "id": 804,
        "main": "Clouds",
        "description": "overcast clouds",
        "icon": "04n"
      }
    ],
    "base": "stations",
    "main": {
      "temp": -13.03,
      "feels_like": -13.03,
      "temp_min": -13.03,
      "temp_max": -13.03,
      "pressure": 1007,
      "humidity": 99,
      "sea_level": 1007,
      "grnd_level": 918
    },
    "visibility": 915,
    "wind": {
      "speed": 1.03,
      "deg": 109,
      "gust": 1.14
    },
    "clouds": {
      "all": 100
    },
    "dt": 1731912654,
    "sys": {
      "country": "CA",
      "sunrise": 1731860303,
      "sunset": 1731887637
    },
    "timezone": -25200,
    "id": 6064168,
    "name": "Magnum Mine",
    "cod": 200
  },
  {
    "coord": {
      "lon": -125.2317,
      "lat": 58.8478
    },
    "weather": [
      {
        "id": 804,
        "main": "Clouds",
        "description": "overcast clouds",
        "icon": "04n"
      }
    ],
    "base": "stations",
    "main": {
      "temp": -15.94,
      "feels_like": -19.6,
      "temp_min": -15.94,
      "temp_max": -15.94,
      "pressure": 1026,
      "humidity": 98,
      "sea_level": 1026,
      "grnd_level": 935
    },
    "visibility": 350,
    "wind": {
      "speed": 1.37,
      "deg": 66,
      "gust": 1.65
    },
    "clouds": {
      "all": 100
    },
    "dt": 1731999031,
    "sys": {
      "country": "CA",
      "sunrise": 1731946842,
      "sunset": 1731973925
    },
    "timezone": -25200,
    "id": 6064168,
    "name": "Magnum Mine",
    "cod": 200
  },
  {
    "coord": {
      "lon": -125.2317,
      "lat": 58.8478
    },
    "weather": [
      {
        "id": 804,
        "main": "Clouds",
        "description": "overcast clouds",
        "icon": "04n"
      }
    ],
    "base": "stations",
    "main": {
      "temp": -24.2,
      "feels_like": -24.2,
      "temp_min": -24.2,
      "temp_max": -24.2,
      "pressure": 1045,
      "humidity": 100,
      "sea_level": 1045,
      "grnd_level": 949
    },
    "visibility": 1491,
    "wind": {
      "speed": 0.88,
      "deg": 122,
      "gust": 0.97
    },
    "clouds": {
      "all": 99
    },
    "dt": 1732085441,
    "sys": {
      "country": "CA",
      "sunrise": 1732033380,
      "sunset": 1732060216
    },
    "timezone": -25200,
    "id": 6064168,
    "name": "Magnum Mine",
    "cod": 200
  },
  {
    "coord": {
      "lon": -125.2317,
      "lat": 58.8478
    },
    "weather": [
      {
        "id": 802,
        "main": "Clouds",
        "description": "scattered clouds",
        "icon": "03n"
      }
    ],
    "base": "stations",
    "main": {
      "temp": -23.6,
      "feels_like": -23.6,
      "temp_min": -23.6,
      "temp_max": -23.6,
      "pressure": 1043,
      "humidity": 95,
      "sea_level": 1043,
      "grnd_level": 947
    },
    "visibility": 10000,
    "wind": {
      "speed": 1.32,
      "deg": 245,
      "gust": 1.11
    },
    "clouds": {
      "all": 33
    },
    "dt": 1732171844,
    "sys": {
      "country": "CA",
      "sunrise": 1732119917,
      "sunset": 1732146509
    },
    "timezone": -25200,
    "id": 6064168,
    "name": "Magnum Mine",
    "cod": 200
  },
  {
    "coord": {
      "lon": -125.2317,
      "lat": 58.8478
    },
    "weather": [
      {
        "id": 801,
        "main": "Clouds",
        "description": "few clouds",
        "icon": "02n"
      }
    ],
    "base": "stations",
    "main": {
      "temp": -18.68,
      "feels_like": -24.44,
      "temp_min": -18.68,
      "temp_max": -18.68,
      "pressure": 1038,
      "humidity": 92,
      "sea_level": 1038,
      "grnd_level": 945
    },
    "visibility": 10000,
    "wind": {
      "speed": 2.11,
      "deg": 234,
      "gust": 1.64
    },
    "clouds": {
      "all": 18
    },
    "dt": 1732258242,
    "sys": {
      "country": "CA",
      "sunrise": 1732206452,
      "sunset": 1732232806
    },
    "timezone": -25200,
    "id": 6064168,
    "name": "Magnum Mine",
    "cod": 200
  },
  {
    "coord": {
      "lon": -125.2317,
      "lat": 58.8478
    },
    "weather": [
      {
        "id": 600,
        "main": "Snow",
        "description": "light snow",
        "icon": "13n"
      }
    ],
    "base": "stations",
    "main": {
      "temp": -14.64,
      "feels_like": -18.52,
      "temp_min": -14.64,
      "temp_max": -14.64,
      "pressure": 1037,
      "humidity": 98,
      "sea_level": 1037,
      "grnd_level": 945
    },
    "visibility": 215,
    "wind": {
      "speed": 1.53,
      "deg": 51,
      "gust": 2.11
    },
    "snow": {
      "1h": 0.19
    },
    "clouds": {
      "all": 100
    },
    "dt": 1732344632,
    "sys": {
      "country": "CA",
      "sunrise": 1732292985,
      "sunset": 1732319105
    },
    "timezone": -25200,
    "id": 6064168,
    "name": "Magnum Mine",
    "cod": 200
  },
  {
    "coord": {
      "lon": -125.2317,
      "lat": 58.8478
    },
    "weather": [
      {
        "id": 801,
        "main": "Clouds",
        "description": "few clouds",
        "icon": "02n"
      }
    ],
    "base": "stations",
    "main": {
      "temp": -22.59,
      "feels_like": -29.59,
      "temp_min": -22.59,
      "temp_max": -22.59,
      "pressure": 1038,
      "humidity": 92,
      "sea_level": 1038,
      "grnd_level": 943
    },
    "visibility": 10000,
    "wind": {
      "speed": 2.47,
      "deg": 230,
      "gust": 1.8
    },
    "clouds": {
      "all": 11
    },
    "dt": 1732430992,
    "sys": {
      "country": "CA",
      "sunrise": 1732379517,
      "sunset": 1732405408
    },
    "timezone": -25200,
    "id": 6064168,
    "name": "Magnum Mine",
    "cod": 200
  }
]