[
  {
    "coord": {
      "lon": -135.1159,
      "lat": 60.6836
    },
    "weather": [
      {
        "id": 600,
        "main": "Snow",
        "description": "light snow",
        "icon": "13n"
      }
    ],
    "base": "stations",
    "main": {
      "temp": -16.14,
      "feels_like": -16.14,
      "temp_min": -16.47,
      "temp_max": -15.45,
      "pressure": 1028,
      "humidity": 80,
      "sea_level": 1028,
      "grnd_level": 930
    },
    "visibility": 10000,
    "wind": {
      "speed": 1.03,
      "deg": 0
    },
    "clouds": {
      "all": 75
    },
    "dt": 1738997334,
    "sys": {
      "type": 1,
      "id": 983,
      "country": "CA",
      "sunrise": 1738947711,
      "sunset": 1738978048
    },
    "timezone": -25200,
    "id": 6180550,
    "name": "Whitehorse",
    "cod": 200
  },
  {
    "coord": {
      "lon": -135.1159,
      "lat": 60.6836
    },
    "weather": [
      {
        "id": 600,
        "main": "Snow",
        "description": "light snow",
        "icon": "13n"
      }
    ],
    "base": "stations",
    "main": {
      "temp": -16.47,
      "feels_like": -16.47,
      "temp_min": -22.51,
      "temp_max": -16.47,
      "pressure": 1043,
      "humidity": 78,
      "sea_level": 1043,
      "grnd_level": 939
    },
    "visibility": 10000,
    "wind": {
      "speed": 1.03,
      "deg": 210
    },
    "clouds": {
      "all": 100
    },
    "dt": 1739083743,
    "sys": {
      "type": 1,
      "id": 983,
      "country": "CA",
      "sunrise": 1739033953,
      "sunset": 1739064613
    },
    "timezone": -25200,
    "id": 6180550,
    "name": "Whitehorse",
    "cod": 200
  },
  {
    "coord": {
      "lon": -135.1159,
      "lat": 60.6836
    },
    "weather": [
      {
        "id": 804,
        "main": "Clouds",
        "description": "overcast clouds",
        "icon": "04n"
      }
    ],
    "base": "stations",
    "main": {
      "temp": -21.47,
      "feels_like": -26.35,
      "temp_min": -21.47,
      "temp_max": -21.29,
      "pressure": 1049,
      "humidity": 77,
      "sea_level": 1049,
      "grnd_level": 945
    },
    "visibility": 10000,
    "wind": {
      "speed": 1.54,
      "deg": 170
    },
    "clouds": {
      "all": 100
    },
    "dt": 1739170176,
    "sys": {
      "type": 1,
      "id": 983,
      "country": "CA",
      "sunrise": 1739120193,
      "sunset": 1739151177
    },
    "timezone": -25200,
    "id": 6180550,
    "name": "Whitehorse",
    "cod": 200
  },
  {
    "coord": {
      "lon": -135.1159,
      "lat": 60.6836
    },
    "weather": [
      {
        "id": 800,
        "main": "Clear",
        "description": "clear sky",
        "icon": "01n"
      }
    ],
    "base": "stations",
    "main": {
      "temp": -23.47,
      "feels_like": -23.47,
      "temp_min": -23.51,
      "temp_max": -23.47,
      "pressure": 1044,
      "humidity": 77,
      "sea_level": 1044,
      "grnd_level": 941
    },
    "visibility": 10000,
    "wind": {
      "speed": 1.03,
      "deg": 270
    },
    "clouds": {
      "all": 0
    },
    "dt": 1739256549,
    "sys": {
      "type": 1,
      "id": 983,
      "country": "CA",
      "sunrise": 1739206431,
      "sunset": 1739237741
    },
    "timezone": -25200,
    "id": 6180550,
    "name": "Whitehorse",
    "cod": 200
  },
  {
    "coord": {
      "lon": -135.1159,
      "lat": 60.6836
    },
    "weather": [
      {
        "id": 800,
        "main": "Clear",
        "description": "clear sky",
        "icon": "01n"
      }
    ],
    "base": "stations",
    "main": {
      "temp": -25.47,
      "feels_like": -25.47,
      "temp_min": -25.47,
      "temp_max": -25.47,
      "pressure": 1030,
      "humidity": 77,
      "sea_level": 1030,
      "grnd_level": 928
    },
    "visibility": 10000,
    "wind": {
      "speed": 1.03,
      "deg": 240
    },
    "clouds": {
      "all": 0
    },
    "dt": 1739342948,
    "sys": {
      "type": 1,
      "id": 983,
      "country": "CA",
      "sunrise": 1739292669,
      "sunset": 1739324306
    },
    "timezone": -25200,
    "id": 6180550,
    "name": "Whitehorse",
    "cod": 200
  },
  {
    "coord": {
      "lon": -135.1159,
      "lat": 60.6836
    },
    "weather": [
      {
        "id": 600,
        "main": "Snow",
        "description": "light snow",
        "icon": "13n"
      }
    ],
    "base": "stations",
    "main": {
      "temp": -16.65,
      "feels_like": -22.86,
      "temp_min": -16.84,
      "temp_max": -15.85,
      "pressure": 1016,
      "humidity": 85,
      "sea_level": 1016,
      "grnd_level": 917
    },
    "visibility": 4828,
    "wind": {
      "speed": 2.57,
      "deg": 340
    },
    "clouds": {
      "all": 100
    },
    "dt": 1739429354,
    "sys": {
      "type": 1,
      "id": 983,
      "country": "CA",
      "sunrise": 1739378905,
      "sunset": 1739410870
    },
    "timezone": -25200,
    "id": 6180550,
    "name": "Whitehorse",
    "cod": 200
  },
  {
    "coord": {
      "lon": -135.1159,
      "lat": 60.6836
    },
    "weather": [
      {
        "id": 803,
        "main": "Clouds",
        "description": "broken clouds",
        "icon": "04n"
      }
    ],
    "base": "stations",
    "main": {
      "temp": -15.47,
      "feels_like": -22.47,
      "temp_min": -15.47,
      "temp_max": -15.47,
      "pressure": 1019,
      "humidity": 72,
      "sea_level": 1019,
      "grnd_level": 917
    },
    "visibility": 10000,
    "wind": {
      "speed": 5.66,
      "deg": 150,
      "gust": 8.75
    },
    "clouds": {
      "all": 75
    },
    "dt": 1739515754,
    "sys": {
      "type": 1,
      "id": 983,
      "country": "CA",
      "sunrise": 1739465139,
      "sunset": 1739497433
    },
    "timezone": -25200,
    "id": 6180550,
    "name": "Whitehorse",
    "cod": 200
  },
  {
    "coord": {
      "lon": -135.1159,
      "lat": 60.6836
    },
    "weather": [
      {
        "id": 800,
        "main": "Clear",
        "description": "clear sky",
        "icon": "01n"
      }
    ],
    "base": "stations",
    "main": {
      "temp": -18.47,
      "feels_like": -25.47,
      "temp_min": -18.47,
      "temp_max": -18.47,
      "pressure": 1033,
      "humidity": 65,
      "sea_level": 1033,
      "grnd_level": 929
    },
    "visibility": 10000,
    "wind": {
      "speed": 8.75,
      "deg": 150,
      "gust": 14.92
    },
    "clouds": {
      "all": 0
    },
    "dt": 1739602139,
    "sys": {
      "type": 1,
      "id": 983,
      "country": "CA",
      "sunrise": 1739551372,
      "sunset": 1739583997
    },
    "timezone": -25200,
    "id": 6180550,
    "name": "Whitehorse",
    "cod": 200
  },
  {
    "coord": {
      "lon": -135.1159,
      "lat": 60.6836
    },
    "weather": [
      {
        "id": 803,
        "main": "Clouds",
        "description": "broken clouds",
        "icon": "04n"
      }
    ],
    "base": "stations",
    "main": {
      "temp": -17.47,
      "feels_like": -24.47,
      "temp_min": -22.51,
      "temp_max": -17.47,
      "pressure": 1026,
      "humidity": 66,
      "sea_level": 1026,
      "grnd_level": 924
    },
    "visibility": 10000,
    "wind": {
      "speed": 7.2,
      "deg": 160,
      "gust": 11.32
    },
    "clouds": {
      "all": 75
    },
    "dt": 1739688535,
    "sys": {
      "type": 1,
      "id": 983,
      "country": "CA",
      "sunrise": 1739637605,
      "sunset": 1739670560
    },
    "timezone": -25200,
    "id": 6180550,
    "name": "Whitehorse",
    "cod": 200
  },
  {
    "coord": {
      "lon": -135.1159,
      "lat": 60.6836
    },
    "weather": [
      {
        "id": 803,
        "main": "Clouds",
        "description": "broken clouds",
        "icon": "04n"
      }
    ],
    "base": "stations",
    "main": {
      "temp": -12.47,
      "feels_like": -19.47,
      "temp_min": -12.47,
      "temp_max": -12.47,
      "pressure": 1023,
      "humidity": 67,
      "sea_level": 1023,
      "grnd_level": 922
    },
    "visibility": 10000,
    "wind": {
      "speed": 6.17,
      "deg": 180
    },
    "clouds": {
      "all": 75
    },
    "dt": 1739775008,
    "sys": {
      "type": 1,
      "id": 983,
      "country": "CA",
      "sunrise": 1739723836,
      "sunset": 1739757122
    },
    "timezone": -25200,
    "id": 6180550,
    "name": "Whitehorse",
    "cod": 200
  }
]