[
  {
    "coord": {
      "lon": -135.1159,
      "lat": 60.6836
    },
    "weather": [
      {
        "id": 803,
        "main": "Clouds",
        "description": "broken clouds",
        "icon": "04n"
      }
    ],
    "base": "stations",
    "main": {
      "temp": 1.27,
      "feels_like": -3.67,
      "temp_min": 0.94,
      "temp_max": 1.53,
      "pressure": 1015,
      "humidity": 87,
      "sea_level": 1015,
      "grnd_level": 922
    },
    "visibility": 10000,
    "wind": {
      "speed": 5.66,
      "deg": 170
    },
    "clouds": {
      "all": 75
    },
    "dt": 1727938201,
    "sys": {
      "type": 1,
      "id": 983,
      "country": "CA",
      "sunrise": 1727881826,
      "sunset": 1727922513
    },
    "timezone": -25200,
    "id": 6180550,
    "name": "Whitehorse",
    "cod": 200
  },
  {
    "coord": {
      "lon": -135.1159,
      "lat": 60.6836
    },
    "weather": [
      {
        "id": 802,
        "main": "Clouds",
        "description": "scattered clouds",
        "icon": "03n"
      }
    ],
    "base": "stations",
    "main": {
      "temp": 2.32,
      "feels_like": -2.35,
      "temp_min": 1.77,
      "temp_max": 2.53,
      "pressure": 1008,
      "humidity": 87,
      "sea_level": 1008,
      "grnd_level": 916
    },
    "visibility": 10000,
    "wind": {
      "speed": 5.66,
      "deg": 170
    },
    "clouds": {
      "all": 40
    },
    "dt": 1728024624,
    "sys": {
      "type": 1,
      "id": 983,
      "country": "CA",
      "sunrise": 1727968373,
      "sunset": 1728008727
    },
    "timezone": -25200,
    "id": 6180550,
    "name": "Whitehorse",
    "cod": 200
  },
  {
    "coord": {
      "lon": -135.1159,
      "lat": 60.6836
    },
    "weather": [
      {
        "id": 801,
        "main": "Clouds",
        "description": "few clouds",
        "icon": "02n"
      }
    ],
    "base": "stations",
    "main": {
      "temp": 2.08,
      "feels_like": -3.32,
      "temp_min": 1.22,
      "temp_max": 2.53,
      "pressure": 1000,
      "humidity": 70,
      "sea_level": 1000,
      "grnd_level": 909
    },
    "visibility": 10000,
    "wind": {
      "speed": 7.2,
      "deg": 160,
      "gust": 10.29
    },
    "clouds": {
      "all": 20
    },
    "dt": 1728110943,
    "sys": {
      "type": 1,
      "id": 983,
      "country": "CA",
      "sunrise": 1728054921,
      "sunset": 1728094941
    },
    "timezone": -25200,
    "id": 6180550,
    "name": "Whitehorse",
    "cod": 200
  },
  {
    "coord": {
      "lon": -135.1159,
      "lat": 60.6836
    },
    "weather": [
      {
        "id": 802,
        "main": "Clouds",
        "description": "scattered clouds",
        "icon": "03n"
      }
    ],
    "base": "stations",
    "main": {
      "temp": 3.14,
      "feels_like": -1.54,
      "temp_min": 1.93,
      "temp_max": 3.53,
      "pressure": 1008,
      "humidity": 69,
      "sea_level": 1008,
      "grnd_level": 915
    },
    "visibility": 10000,
    "wind": {
      "speed": 6.17,
      "deg": 190
    },
    "clouds": {
      "all": 40
    },
    "dt": 1728197355,
    "sys": {
      "type": 1,
      "id": 983,
      "country": "CA",
      "sunrise": 1728141469,
      "sunset": 1728181156
    },
    "timezone": -25200,
    "id": 6180550,
    "name": "Whitehorse",
    "cod": 200
  },
  {
    "coord": {
      "lon": -135.1159,
      "lat": 60.6836
    },
    "weather": [
      {
        "id": 804,
        "main": "Clouds",
        "description": "overcast clouds",
        "icon": "04n"
      }
    ],
    "base": "stations",
    "main": {
      "temp": 1.92,
      "feels_like": -1.44,
      "temp_min": 1.92,
      "temp_max": 1.92,
      "pressure": 997,
      "humidity": 92,
      "sea_level": 997,
      "grnd_level": 906
    },
    "visibility": 10000,
    "wind": {
      "speed": 3.31,
      "deg": 151,
      "gust": 7.01
    },
    "clouds": {
      "all": 86
    },
    "dt": 1728283820,
    "sys": {
      "country": "CA",
      "sunrise": 1728228018,
      "sunset": 1728267372
    },
    "timezone": -25200,
    "id": 6180550,
    "name": "Whitehorse",
    "cod": 200
  },
  {
    "coord": {
      "lon": -135.1159,
      "lat": 60.6836
    },
    "weather": [
      {
        "id": 804,
        "main": "Clouds",
        "description": "overcast clouds",
        "icon": "04n"
      }
    ],
    "base": "stations",
    "main": {
      "temp": 3.36,
      "feels_like": 0.89,
      "temp_min": 1.77,
      "temp_max": 3.53,
      "pressure": 1003,
      "humidity": 70,
      "sea_level": 1003,
      "grnd_level": 911
    },
    "visibility": 10000,
    "wind": {
      "speed": 2.57,
      "deg": 160
    },
    "clouds": {
      "all": 100
    },
    "dt": 1728370212,
    "sys": {
      "type": 1,
      "id": 983,
      "country": "CA",
      "sunrise": 1728314566,
      "sunset": 1728353588
    },
    "timezone": -25200,
    "id": 6180550,
    "name": "Whitehorse",
    "cod": 200
  },
  {
    "coord": {
      "lon": -135.1159,
      "lat": 60.6836
    },
    "weather": [
      {
        "id": 804,
        "main": "Clouds",
        "description": "overcast clouds",
        "icon": "04n"
      }
    ],
    "base": "stations",
    "main": {
      "temp": -0.59,
      "feels_like": -0.59,
      "temp_min": -0.73,
      "temp_max": 0.11,
      "pressure": 1005,
      "humidity": 93,
      "sea_level": 1005,
      "grnd_level": 913
    },
    "visibility": 10000,
    "wind": {
      "speed": 0,
      "deg": 0
    },
    "clouds": {
      "all": 100
    },
    "dt": 1728456613,
    "sys": {
      "type": 1,
      "id": 983,
      "country": "CA",
      "sunrise": 1728401116,
      "sunset": 1728439804
    },
    "timezone": -25200,
    "id": 6180550,
    "name": "Whitehorse",
    "cod": 200
  },
  {
    "coord": {
      "lon": -135.1159,
      "lat": 60.6836
    },
    "weather": [
      {
        "id": 804,
        "main": "Clouds",
        "description": "overcast clouds",
        "icon": "04n"
      }
    ],
    "base": "stations",
    "main": {
      "temp": 3.53,
      "feels_like": -0.82,
      "temp_min": 2.33,
      "temp_max": 3.53,
      "pressure": 1012,
      "humidity": 70,
      "sea_level": 1012,
      "grnd_level": 919
    },
    "visibility": 10000,
    "wind": {
      "speed": 5.66,
      "deg": 160
    },
    "clouds": {
      "all": 100
    },
    "dt": 1728543004,
    "sys": {
      "type": 1,
      "id": 983,
      "country": "CA",
      "sunrise": 1728487665,
      "sunset": 1728526021
    },
    "timezone": -25200,
    "id": 6180550,
    "name": "Whitehorse",
    "cod": 200
  },
  {
    "coord": {
      "lon": -135.1159,
      "lat": 60.6836
    },
    "weather": [
      {
        "id": 803,
        "main": "Clouds",
        "description": "broken clouds",
        "icon": "04n"
      }
    ],
    "base": "stations",
    "main": {
      "temp": 2.81,
      "feels_like": -1.47,
      "temp_min": 1.77,
      "temp_max": 3.16,
      "pressure": 1014,
      "humidity": 67,
      "sea_level": 1014,
      "grnd_level": 921
    },
    "visibility": 10000,
    "wind": {
      "speed": 5.14,
      "deg": 160,
      "gust": 7.72
    },
    "clouds": {
      "all": 75
    },
    "dt": 1728629399,
    "sys": {
      "type": 1,
      "id": 983,
      "country": "CA",
      "sunrise": 1728574216,
      "sunset": 1728612239
    },
    "timezone": -25200,
    "id": 6180550,
    "name": "Whitehorse",
    "cod": 200
  },
  {
    "coord": {
      "lon": -135.1159,
      "lat": 60.6836
    },
    "weather": [
      {
        "id": 803,
        "main": "Clouds",
        "description": "broken clouds",
        "icon": "04n"
      }
    ],
    "base": "stations",
    "main": {
      "temp": 2.32,
      "feels_like": -3.73,
      "temp_min": 1.77,
      "temp_max": 2.53,
      "pressure": 1012,
      "humidity": 56,
      "sea_level": 1012,
      "grnd_level": 919
    },
    "visibility": 10000,
    "wind": {
      "speed": 9.26,
      "deg": 160
    },
    "clouds": {
      "all": 75
    },
    "dt": 1728715736,
    "sys": {
      "type": 1,
      "id": 983,
      "country": "CA",
      "sunrise": 1728660766,
      "sunset": 1728698457
    },
    "timezone": -25200,
    "id": 6180550,
    "name": "Whitehorse",
    "cod": 200
  }
]