[
  {
    "coord": {
      "lon": -135.1159,
      "lat": 60.6836
    },
    "weather": [
      {
        "id": 801,
        "main": "Clouds",
        "description": "few clouds",
        "icon": "02n"
      }
    ],
    "base": "stations",
    "main": {
      "temp": -17.59,
      "feels_like": -24.59,
      "temp_min": -22.51,
      "temp_max": -17.12,
      "pressure": 1014,
      "humidity": 82
    },
    "visibility": 10000,
    "wind": {
      "speed": 6.17,
      "deg": 190
    },
    "clouds": {
      "all": 20
    },
    "dt": 1707461337,
    "sys": {
      "type": 1,
      "id": 983,
      "country": "CA",
      "sunrise": 1707411671,
      "sunset": 1707442090
    },
    "timezone": -25200,
    "id": 6180550,
    "name": "Whitehorse",
    "cod": 200
  },
  {
    "coord": {
      "lon": -135.1159,
      "lat": 60.6836
    },
    "weather": [
      {
        "id": 801,
        "main": "Clouds",
        "description": "few clouds",
        "icon": "02n"
      }
    ],
    "base": "stations",
    "main": {
      "temp": -8.73,
      "feels_like": -15.73,
      "temp_min": -9.06,
      "temp_max": -7.67,
      "pressure": 996,
      "humidity": 86
    },
    "visibility": 10000,
    "wind": {
      "speed": 9.26,
      "deg": 170
    },
    "clouds": {
      "all": 20
    },
    "dt": 1707547742,
    "sys": {
      "type": 1,
      "id": 983,
      "country": "CA",
      "sunrise": 1707497912,
      "sunset": 1707528655
    },
    "timezone": -25200,
    "id": 6180550,
    "name": "Whitehorse",
    "cod": 200
  },
  {
    "coord": {
      "lon": -135.1159,
      "lat": 60.6836
    },
    "weather": [
      {
        "id": 801,
        "main": "Clouds",
        "description": "few clouds",
        "icon": "02n"
      }
    ],
    "base": "stations",
    "main": {
      "temp": -2.47,
      "feels_like": -8.09,
      "temp_min": -2.47,
      "temp_max": -2.47,
      "pressure": 1005,
      "humidity": 80
    },
    "visibility": 10000,
    "wind": {
      "speed": 5.14,
      "deg": 150
    },
    "clouds": {
      "all": 20
    },
    "dt": 1707634140,
    "sys": {
      "type": 1,
      "id": 983,
      "country": "CA",
      "sunrise": 1707584152,
      "sunset": 1707615219
    },
    "timezone": -25200,
    "id": 6180550,
    "name": "Whitehorse",
    "cod": 200
  },
  {
    "coord": {
      "lon": -135.1159,
      "lat": 60.6836
    },
    "weather": [
      {
        "id": 803,
        "main": "Clouds",
        "description": "broken clouds",
        "icon": "04n"
      }
    ],
    "base": "stations",
    "main": {
      "temp": -3.47,
      "feels_like": -9.01,
      "temp_min": -3.47,
      "temp_max": -3.47,
      "pressure": 1009,
      "humidity": 50
    },
    "visibility": 10000,
    "wind": {
      "speed": 4.63,
      "deg": 170
    },
    "clouds": {
      "all": 75
    },
    "dt": 1707720537,
    "sys": {
      "type": 1,
      "id": 983,
      "country": "CA",
      "sunrise": 1707670390,
      "sunset": 1707701784
    },
    "timezone": -25200,
    "id": 6180550,
    "name": "Whitehorse",
    "cod": 200
  },
  {
    "coord": {
      "lon": -135.1159,
      "lat": 60.6836
    },
    "weather": [
      {
        "id": 803,
        "main": "Clouds",
        "description": "broken clouds",
        "icon": "04n"
      }
    ],
    "base": "stations",
    "main": {
      "temp": -5.47,
      "feels_like": -5.47,
      "temp_min": -9.79,
      "temp_max": -5.47,
      "pressure": 1022,
      "humidity": 68
    },
    "visibility": 10000,
    "wind": {
      "speed": 1.03,
      "deg": 0
    },
    "clouds": {
      "all": 75
    },
    "dt": 1707806940,
    "sys": {
      "type": 1,
      "id": 983,
      "country": "CA",
      "sunrise": 1707756627,
      "sunset": 1707788348
    },
    "timezone": -25200,
    "id": 6180550,
    "name": "Whitehorse",
    "cod": 200
  },
  {
    "coord": {
      "lon": -135.1159,
      "lat": 60.6836
    },
    "weather": [
      {
        "id": 803,
        "main": "Clouds",
        "description": "broken clouds",
        "icon": "04n"
      }
    ],
    "base": "stations",
    "main": {
      "temp": -7.47,
      "feels_like": -14.47,
      "temp_min": -7.47,
      "temp_max": -7.47,
      "pressure": 1023,
      "humidity": 79
    },
    "visibility": 10000,
    "wind": {
      "speed": 6.17,
      "deg": 180
    },
    "clouds": {
      "all": 75
    },
    "dt": 1707893337,
    "sys": {
      "type": 1,
      "id": 983,
      "country": "CA",
      "sunrise": 1707842862,
      "sunset": 1707874912
    },
    "timezone": -25200,
    "id": 6180550,
    "name": "Whitehorse",
    "cod": 200
  },
  {
    "coord": {
      "lon": -135.1159,
      "lat": 60.6836
    },
    "weather": [
      {
        "id": 801,
        "main": "Clouds",
        "description": "few clouds",
        "icon": "02n"
      }
    ],
    "base": "stations",
    "main": {
      "temp": -16.65,
      "feels_like": -16.65,
      "temp_min": -16.96,
      "temp_max": -16.47,
      "pressure": 1024,
      "humidity": 85
    },
    "visibility": 10000,
    "wind": {
      "speed": 1.03,
      "deg": 0
    },
    "clouds": {
      "all": 20
    },
    "dt": 1707979737,
    "sys": {
      "type": 1,
      "id": 983,
      "country": "CA",
      "sunrise": 1707929097,
      "sunset": 1707961475
    },
    "timezone": -25200,
    "id": 6180550,
    "name": "Whitehorse",
    "cod": 200
  },
  {
    "coord": {
      "lon": -135.1159,
      "lat": 60.6836
    },
    "weather": [
      {
        "id": 800,
        "main": "Clear",
        "description": "clear sky",
        "icon": "01n"
      }
    ],
    "base": "stations",
    "main": {
      "temp": -10.6,
      "feels_like": -17.6,
      "temp_min": -15.29,
      "temp_max": -10.47,
      "pressure": 1022,
      "humidity": 79
    },
    "visibility": 10000,
    "wind": {
      "speed": 11.32,
      "deg": 180,
      "gust": 13.89
    },
    "clouds": {
      "all": 0
    },
    "dt": 1708066139,
    "sys": {
      "type": 1,
      "id": 983,
      "country": "CA",
      "sunrise": 1708015330,
      "sunset": 1708048038
    },
    "timezone": -25200,
    "id": 6180550,
    "name": "Whitehorse",
    "cod": 200
  },
  {
    "coord": {
      "lon": -135.1159,
      "lat": 60.6836
    },
    "weather": [
      {
        "id": 800,
        "main": "Clear",
        "description": "clear sky",
        "icon": "01n"
      }
    ],
    "base": "stations",
    "main": {
      "temp": -8.21,
      "feels_like": -15.21,
      "temp_min": -15.85,
      "temp_max": -7.47,
      "pressure": 1016,
      "humidity": 63
    },
    "visibility": 10000,
    "wind": {
      "speed": 8.75,
      "deg": 180,
      "gust": 11.83
    },
    "clouds": {
      "all": 0
    },
    "dt": 1708152534,
    "sys": {
      "type": 1,
      "id": 983,
      "country": "CA",
      "sunrise": 1708101561,
      "sunset": 1708134601
    },
    "timezone": -25200,
    "id": 6180550,
    "name": "Whitehorse",
    "cod": 200
  },
  {
    "coord": {
      "lon": -135.1159,
      "lat": 60.6836
    },
    "weather": [
      {
        "id": 800,
        "main": "Clear",
        "description": "clear sky",
        "icon": "01n"
      }
    ],
    "base": "stations",
    "main": {
      "temp": -11.07,
      "feels_like": -11.07,
      "temp_min": -14.18,
      "temp_max": -8.78,
      "pressure": 1008,
      "humidity": 74
    },
    "visibility": 10000,
    "wind": {
      "speed": 1.03,
      "deg": 0
    },
    "clouds": {
      "all": 0
    },
    "dt": 1708238936,
    "sys": {
      "type": 1,
      "id": 983,
      "country": "CA",
      "sunrise": 1708187792,
      "sunset": 1708221164
    },
    "timezone": -25200,
    "id": 6180550,
    "name": "Whitehorse",
    "cod": 200
  }
]