[
  {
    "coord": {
      "lon": -135.1159,
      "lat": 60.6836
    },
    "weather": [
      {
        "id": 600,
        "main": "Snow",
        "description": "light snow",
        "icon": "13n"
      },
      {
        "id": 701,
        "main": "Mist",
        "description": "mist",
        "icon": "50n"
      }
    ],
    "base": "stations",
    "main": {
      "temp": -29.47,
      "feels_like": -36.47,
      "temp_min": -29.47,
      "temp_max": -24.73,
      "pressure": 1028,
      "humidity": 76,
      "sea_level": 1028,
      "grnd_level": 925
    },
    "visibility": 4023,
    "wind": {
      "speed": 2.06,
      "deg": 360
    },
    "clouds": {
      "all": 100
    },
    "dt": 1766732102,
    "sys": {
      "type": 1,
      "id": 983,
      "country": "CA",
      "sunrise": 1766686248,
      "sunset": 1766706632
    },
    "timezone": -25200,
    "id": 6180550,
    "name": "Whitehorse",
    "cod": 200
  },
  {
    "coord": {
      "lon": -135.1159,
      "lat": 60.6836
    },
    "weather": [
      {
        "id": 804,
        "main": "Clouds",
        "description": "overcast clouds",
        "icon": "04n"
      }
    ],
    "base": "stations",
    "main": {
      "temp": -27.47,
      "feels_like": -34.47,
      "temp_min": -27.47,
      "temp_max": -27.4,
      "pressure": 1026,
      "humidity": 76,
      "sea_level": 1026,
      "grnd_level": 923
    },
    "visibility": 10000,
    "wind": {
      "speed": 8.75,
      "deg": 170,
      "gust": 11.83
    },
    "clouds": {
      "all": 100
    },
    "dt": 1766818429,
    "sys": {
      "type": 1,
      "id": 983,
      "country": "CA",
      "sunrise": 1766772651,
      "sunset": 1766793086
    },
    "timezone": -25200,
    "id": 6180550,
    "name": "Whitehorse",
    "cod": 200
  },
  {
    "coord": {
      "lon": -135.1159,
      "lat": 60.6836
    },
    "weather": [
      {
        "id": 600,
        "main": "Snow",
        "description": "light snow",
        "icon": "13n"
      }
    ],
    "base": "stations",
    "main": {
      "temp": -21.47,
      "feels_like": -28.47,
      "temp_min": -21.47,
      "temp_max": -21.29,
      "pressure": 1015,
      "humidity": 77,
      "sea_level": 1015,
      "grnd_level": 915
    },
    "visibility": 1609,
    "wind": {
      "speed": 2.57,
      "deg": 350
    },
    "snow": {
      "1h": 0.28
    },
    "clouds": {
      "all": 100
    },
    "dt": 1766904841,
    "sys": {
      "type": 1,
      "id": 983,
      "country": "CA",
      "sunrise": 1766859048,
      "sunset": 1766879546
    },
    "timezone": -25200,
    "id": 6180550,
    "name": "Whitehorse",
    "cod": 200
  },
  {
    "coord": {
      "lon": -135.1159,
      "lat": 60.6836
    },
    "weather": [
      {
        "id": 600,
        "main": "Snow",
        "description": "light snow",
        "icon": "13n"
      }
    ],
    "base": "stations",
    "main": {
      "temp": -23.49,
      "feels_like": -30.49,
      "temp_min": -23.62,
      "temp_max": -23.47,
      "pressure": 1023,
      "humidity": 77,
      "sea_level": 1023,
      "grnd_level": 920
    },
    "visibility": 4023,
    "wind": {
      "speed": 5.14,
      "deg": 340
    },
    "snow": {
      "1h": 0.14
    },
    "clouds": {
      "all": 100
    },
    "dt": 1766991422,
    "sys": {
      "type": 1,
      "id": 983,
      "country": "CA",
      "sunrise": 1766945439,
      "sunset": 1766966012
    },
    "timezone": -25200,
    "id": 6180550,
    "name": "Whitehorse",
    "cod": 200
  },
  {
    "coord": {
      "lon": -135.1159,
      "lat": 60.6836
    },
    "weather": [
      {
        "id": 804,
        "main": "Clouds",
        "description": "overcast clouds",
        "icon": "04n"
      }
    ],
    "base": "stations",
    "main": {
      "temp": -29.47,
      "feels_like": -36.47,
      "temp_min": -29.62,
      "temp_max": -29.47,
      "pressure": 1028,
      "humidity": 76,
      "sea_level": 1028,
      "grnd_level": 924
    },
    "visibility": 10000,
    "wind": {
      "speed": 2.06,
      "deg": 300
    },
    "clouds": {
      "all": 100
    },
    "dt": 1767077727,
    "sys": {
      "type": 1,
      "id": 983,
      "country": "CA",
      "sunrise": 1767031825,
      "sunset": 1767052483
    },
    "timezone": -25200,
    "id": 6180550,
    "name": "Whitehorse",
    "cod": 200
  },
  {
    "coord": {
      "lon": -135.1159,
      "lat": 60.6836
    },
    "weather": [
      {
        "id": 600,
        "main": "Snow",
        "description": "light snow",
        "icon": "13n"
      }
    ],
    "base": "stations",
    "main": {
      "temp": -23.47,
      "feels_like": -29.93,
      "temp_min": -23.51,
      "temp_max": -23.47,
      "pressure": 1016,
      "humidity": 77,
      "sea_level": 1016,
      "grnd_level": 915
    },
    "visibility": 10000,
    "wind": {
      "speed": 2.06,
      "deg": 330
    },
    "snow": {
      "1h": 0.15
    },
    "clouds": {
      "all": 100
    },
    "dt": 1767164149,
    "sys": {
      "type": 1,
      "id": 983,
      "country": "CA",
      "sunrise": 1767118205,
      "sunset": 1767138959
    },
    "timezone": -25200,
    "id": 6180550,
    "name": "Whitehorse",
    "cod": 200
  },
  {
    "coord": {
      "lon": -135.1159,
      "lat": 60.6836
    },
    "weather": [
      {
        "id": 600,
        "main": "Snow",
        "description": "light snow",
        "icon": "13n"
      }
    ],
    "base": "stations",
    "main": {
      "temp": -21.39,
      "feels_like": -28.39,
      "temp_min": -21.56,
      "temp_max": -21.29,
      "pressure": 1030,
      "humidity": 77,
      "sea_level": 1030,
      "grnd_level": 928
    },
    "visibility": 2414,
    "wind": {
      "speed": 6.17,
      "deg": 350,
      "gust": 10.29
    },
    "clouds": {
      "all": 100
    },
    "dt": 1767250539,
    "sys": {
      "type": 1,
      "id": 983,
      "country": "CA",
      "sunrise": 1767204579,
      "sunset": 1767225441
    },
    "timezone": -25200,
    "id": 6180550,
    "name": "Whitehorse",
    "cod": 200
  },
  {
    "coord": {
      "lon": -135.1159,
      "lat": 60.6836
    },
    "weather": [
      {
        "id": 600,
        "main": "Snow",
        "description": "light snow",
        "icon": "13n"
      }
    ],
    "base": "stations",
    "main": {
      "temp": -23.49,
      "feels_like": -30.49,
      "temp_min": -23.51,
      "temp_max": -23.23,
      "pressure": 1029,
      "humidity": 84,
      "sea_level": 1029,
      "grnd_level": 926
    },
    "visibility": 3219,
    "wind": {
      "speed": 2.57,
      "deg": 360
    },
    "clouds": {
      "all": 100
    },
    "dt": 1767336960,
    "sys": {
      "type": 1,
      "id": 983,
      "country": "CA",
      "sunrise": 1767290948,
      "sunset": 1767311927
    },
    "timezone": -25200,
    "id": 6180550,
    "name": "Whitehorse",
    "cod": 200
  },
  {
    "coord": {
      "lon": -135.1159,
      "lat": 60.6836
    },
    "weather": [
      {
        "id": 600,
        "main": "Snow",
        "description": "light snow",
        "icon": "13n"
      }
    ],
    "base": "stations",
    "main": {
      "temp": -25.59,
      "feels_like": -32.59,
      "temp_min": -25.73,
      "temp_max": -25.45,
      "pressure": 1026,
      "humidity": 76,
      "sea_level": 1026,
      "grnd_level": 922
    },
    "visibility": 10000,
    "wind": {
      "speed": 2.57,
      "deg": 350
    },
    "clouds": {
      "all": 100
    },
    "dt": 1767423240,
    "sys": {
      "type": 1,
      "id": 983,
      "country": "CA",
      "sunrise": 1767377312,
      "sunset": 1767398418
    },
    "timezone": -25200,
    "id": 6180550,
    "name": "Whitehorse",
    "cod": 200
  },
  {
    "coord": {
      "lon": -135.1159,
      "lat": 60.6836
    },
    "weather": [
      {
        "id": 600,
        "main": "Snow",
        "description": "light snow",
        "icon": "13n"
      }
    ],
    "base": "stations",
    "main": {
      "temp": -30.57,
      "feels_like": -37.57,
      "temp_min": -30.73,
      "temp_max": -29.18,
      "pressure": 1017,
      "humidity": 70,
      "sea_level": 1017,
      "grnd_level": 913
    },
    "visibility": 10000,
    "wind": {
      "speed": 2.57,
      "deg": 350
    },
    "clouds": {
      "all": 100
    },
    "dt": 1767509690,
    "sys": {
      "type": 1,
      "id": 983,
      "country": "CA",
      "sunrise": 1767463670,
      "sunset": 1767484914
    },
    "timezone": -25200,
    "id": 6180550,
    "name": "Whitehorse",
    "cod": 200
  }
]