{"coord":{"lon":-125.2317,"lat":58.8478},"weather":[{"id":802,"main":"Clouds","description":"scattered clouds","icon":"03n"}],"base":"stations","main":{"temp":-3.51,"feels_like":-6.25,"temp_min":-3.51,"temp_max":-3.51,"pressure":1012,"humidity":87,"sea_level":1012,"grnd_level":926},"visibility":10000,"wind":{"speed":1.8,"deg":225,"gust":1.48},"clouds":{"all":25},"dt":1711262950,"sys":{"country":"CA","sunrise":1711203119,"sunset":1711248150},"timezone":-25200,"id":6064168,"name":"Magnum Mine","cod":200}