{"coord":{"lon":-125.2317,"lat":58.8478},"weather":[{"id":804,"main":"Clouds","description":"overcast clouds","icon":"04n"}],"base":"stations","main":{"temp":5.72,"feels_like":4.02,"temp_min":5.72,"temp_max":5.72,"pressure":997,"humidity":84,"sea_level":997,"grnd_level":915},"visibility":10000,"wind":{"speed":2.19,"deg":215,"gust":2.26},"clouds":{"all":100},"dt":1697611750,"sys":{"country":"CA","sunrise":1697554920,"sunset":1697591414},"timezone":-25200,"id":6064168,"name":"Magnum Mine","cod":200}