{"coord":{"lon":-125.2317,"lat":58.8478},"weather":[{"id":802,"main":"Clouds","description":"scattered clouds","icon":"03n"}],"base":"stations","main":{"temp":-9.5,"feels_like":-14.5,"temp_min":-9.5,"temp_max":-9.5,"pressure":1025,"humidity":91,"sea_level":1025,"grnd_level":936},"visibility":10000,"wind":{"speed":2.67,"deg":225,"gust":2.03},"clouds":{"all":47},"dt":1646376810,"sys":{"country":"CA","sunrise":1646320278,"sunset":1646358881},"timezone":-25200,"id":6064168,"name":"Magnum Mine","cod":200}