{"coord":{"lon":-125.2317,"lat":58.8478},"weather":[{"id":801,"main":"Clouds","description":"few clouds","icon":"02n"}],"base":"stations","main":{"temp":-7.69,"feels_like":-12.85,"temp_min":-7.69,"temp_max":-7.69,"pressure":999,"humidity":88,"sea_level":999,"grnd_level":913},"visibility":10000,"wind":{"speed":3.1,"deg":221,"gust":3.68},"clouds":{"all":22},"dt":1667544740,"sys":{"country":"CA","sunrise":1667490211,"sunset":1667521523},"timezone":-25200,"id":6064168,"name":"Magnum Mine","cod":200}