{"coord":{"lon":-125.2317,"lat":58.8478},"weather":[{"id":804,"main":"Clouds","description":"overcast clouds","icon":"04n"}],"base":"stations","main":{"temp":-2.9,"feels_like":-2.9,"temp_min":-2.9,"temp_max":-2.9,"pressure":1007,"humidity":86,"sea_level":1007,"grnd_level":922},"visibility":10000,"wind":{"speed":0.82,"deg":288,"gust":0.9},"clouds":{"all":97},"dt":1730098222,"sys":{"country":"CA","sunrise":1730042860,"sunset":1730076095},"timezone":-25200,"id":6064168,"name":"Magnum Mine","cod":200}