{"coord":{"lon":-125.2317,"lat":58.8478},"weather":[{"id":802,"main":"Clouds","description":"scattered clouds","icon":"03n"}],"base":"stations","main":{"temp":3.68,"feels_like":1.15,"temp_min":3.68,"temp_max":3.68,"pressure":1015,"humidity":74,"sea_level":1015,"grnd_level":931},"visibility":10000,"wind":{"speed":2.72,"deg":214,"gust":2.82},"clouds":{"all":36},"dt":1746859810,"sys":{"country":"CA","sunrise":1746792219,"sunset":1746851465},"timezone":-25200,"id":6064168,"name":"Magnum Mine","cod":200}